src/washing_machine.v
module washing_machine (
    input clk,
    input reset,
    input start_stop,
    input cycle_select,
    input door_open,
    output reg [1:0] led_cycle,
    output reg [2:0] led_state,
    output reg door_lock,
    output reg buzzer,
    output reg [3:0] timer_display
);

    // State encoding
    localparam IDLE    = 3'b000;
    localparam FILL    = 3'b001;
    localparam WASH    = 3'b010;
    localparam DRAIN   = 3'b011;
    localparam RINSE   = 3'b100;
    localparam SPIN    = 3'b101;
    localparam PAUSED  = 3'b110;
    localparam COMPLETE= 3'b111;

    reg [2:0] current_state, next_state;

    // Cycle encoding
    localparam DELICATE = 2'b00;
    localparam NORMAL   = 2'b01;
    localparam HEAVY    = 2'b10;

    reg [1:0] selected_cycle;

    // Timers
    reg [5:0] timer;
    reg [5:0] fill_time, wash_time, drain_time, rinse_time, spin_time;

    // Update cycle parameters
    always @(*) begin
        case (selected_cycle)
            DELICATE: {fill_time, wash_time, drain_time, rinse_time, spin_time} = {6'd5, 6'd10, 6'd3, 6'd5, 6'd8};
            NORMAL:   {fill_time, wash_time, drain_time, rinse_time, spin_time} = {6'd7, 6'd15, 6'd5, 6'd7, 6'd12};
            HEAVY:    {fill_time, wash_time, drain_time, rinse_time, spin_time} = {6'd8, 6'd20, 6'd7, 6'd10, 6'd15};
            default:  {fill_time, wash_time, drain_time, rinse_time, spin_time} = {6'd5, 6'd10, 6'd3, 6'd5, 6'd8};
        endcase
    end

    // Reset timer on state change
    reg state_changed;
    always @(posedge clk) begin
        state_changed <= (current_state != next_state);
    end

    // State transition and timer logic
    always @(posedge clk or posedge reset) begin
        if (reset) begin
            current_state <= IDLE;
            timer <= 0;
            selected_cycle <= DELICATE;
        end else begin
            current_state <= next_state;
            if (state_changed) begin
                timer <= 0;  // Reset timer on state change
            end else begin
                case (current_state)
                    FILL:  timer <= (timer < fill_time-1) ? timer + 1 : timer;
                    WASH:  timer <= (timer < wash_time-1) ? timer + 1 : timer;
                    DRAIN: timer <= (timer < drain_time-1) ? timer + 1 : timer;
                    RINSE: timer <= (timer < rinse_time-1) ? timer + 1 : timer;
                    SPIN:  timer <= (timer < spin_time-1) ? timer + 1 : timer;
                    default: timer <= 0;
                endcase
            end
        end
    end

    // LED state output
    always @(*) begin
        case (current_state)
            IDLE:     led_state = IDLE;
            FILL:     led_state = FILL;
            WASH:     led_state = WASH;
            DRAIN:    led_state = DRAIN;
            RINSE:    led_state = RINSE;
            SPIN:     led_state = SPIN;
            PAUSED:   led_state = PAUSED;
            COMPLETE: led_state = COMPLETE;
            default:  led_state = IDLE;
        endcase
    end

    // Cycle selection logic
    always @(posedge clk or posedge reset) begin
        if (reset) begin
            selected_cycle <= DELICATE;
        end else if (current_state == IDLE && cycle_select) begin
            case (selected_cycle)
                DELICATE: selected_cycle <= NORMAL;
                NORMAL:   selected_cycle <= HEAVY;
                HEAVY:    selected_cycle <= DELICATE;
                default:  selected_cycle <= DELICATE;
            endcase
        end
    end

    // LED cycle output
    always @(*) begin
        led_cycle = selected_cycle;
    end

    // Output control logic
    always @(*) begin
        // Default assignments
        next_state = current_state;
        door_lock = (current_state != IDLE && current_state != COMPLETE && current_state != PAUSED);
        buzzer = (current_state == PAUSED || current_state == COMPLETE);
        timer_display = timer;
        
        case (current_state)
            IDLE: begin
                if (start_stop && !door_open) next_state = FILL;
            end
            FILL: begin
                if (door_open) next_state = PAUSED;
                else if (timer >= fill_time-1) next_state = WASH;
            end
            WASH: begin
                if (door_open) next_state = PAUSED;
                else if (timer >= wash_time-1) next_state = DRAIN;
            end
            DRAIN: begin
                if (door_open) next_state = PAUSED;
                else if (timer >= drain_time-1) next_state = RINSE;
            end
            RINSE: begin
                if (door_open) next_state = PAUSED;
                else if (timer >= rinse_time-1) next_state = SPIN;
            end
            SPIN: begin
                if (door_open) next_state = PAUSED;
                else if (timer >= spin_time-1) next_state = COMPLETE;
            end
            PAUSED: begin
                if (!door_open && start_stop) next_state = current_state;
            end
            COMPLETE: begin
                if (start_stop) next_state = IDLE;
            end
        endcase
    end

endmodule

testbench/tb_washing_machine.v
`timescale 1ns/1ps

module tb_washing_machine;
    // State definitions for readability 
    localparam IDLE     = 3'b000;
    localparam FILL     = 3'b001;
    localparam WASH     = 3'b010;
    localparam DRAIN    = 3'b011;
    localparam RINSE    = 3'b100;
    localparam SPIN     = 3'b101;
    localparam PAUSED   = 3'b110;
    localparam COMPLETE = 3'b111;

    // Cycle timing constants
    localparam FILL_TIME  = 4'd5;
    localparam WASH_TIME  = 4'd10;
    localparam DRAIN_TIME = 4'd3;
    localparam RINSE_TIME = 4'd5;
    localparam SPIN_TIME  = 4'd8;

    // Test signals
    reg clk;
    reg reset;
    reg start_stop;
    reg cycle_select;
    reg door_open;

    // DUT outputs
    wire [1:0] led_cycle;
    wire [2:0] led_state;
    wire door_lock;
    wire buzzer;
    wire [3:0] timer_display;

    // Previous state storage
    reg [2:0] prev_state;
    reg [1:0] prev_cycle;
    reg prev_door_lock;
    reg prev_buzzer; 
    reg [3:0] prev_timer;

    // For verification
    integer error_count = 0;

    // Task to check timer values with state name as parametery
    task check_timer;
        input [3:0] expected;
        input [64*8-1:0] state_name;  // 64 character string as bits
        begin
            if(timer_display !== expected) begin
                $display("ERROR: %s timer mismatch - Expected: %0d, Got: %0d at time %0t",
                    state_name, expected, timer_display, $time);
                error_count = error_count + 1;
            end
        end
    endtask

    // Task to print state transitions
    task print_state;
        input [2:0] state;
        begin
            case(state)
                IDLE:     $write("IDLE    ");
                FILL:     $write("FILL    ");
                WASH:     $write("WASH    ");
                DRAIN:    $write("DRAIN   ");
                RINSE:    $write("RINSE   ");
                SPIN:     $write("SPIN    ");
                PAUSED:   $write("PAUSED  ");
                COMPLETE: $write("COMPLETE");
                default:  $write("UNKNOWN ");
            endcase
        end
    endtask

    // Create a task for state transition verification
    task wait_for_state;
        input [2:0] expected_state;
        input [31:0] timeout;  // Timeout in ns
        begin : wait_state    // Add the block label here
            repeat(timeout) @(posedge clk)
            if (led_state == expected_state) begin
                disable wait_state;
            end
        end
    endtask

    // Instantiate washing machine
    washing_machine uut (
        .clk(clk),
        .reset(reset),
        .start_stop(start_stop),
        .cycle_select(cycle_select),
        .door_open(door_open),
        .led_cycle(led_cycle),
        .led_state(led_state),
        .door_lock(door_lock),
        .buzzer(buzzer),
        .timer_display(timer_display)
    );

    // Clock generation
    always #10 clk = ~clk;

    // Monitor state changes with decoded state names
    always @(posedge clk) begin
        if (led_state != prev_state || led_cycle != prev_cycle || 
            door_lock != prev_door_lock || buzzer != prev_buzzer ||
            timer_display != prev_timer) begin
            
            $write("Time: %0t ns | State: ", $time);
            print_state(led_state);
            $display(" | Cycle: %b | Timer: %d | Door Lock: %b | Buzzer: %b",
                led_cycle, timer_display, door_lock, buzzer);
            
            // Update previous values
            prev_state <= led_state;
            prev_cycle <= led_cycle;
            prev_door_lock <= door_lock;
            prev_buzzer <= buzzer;
            prev_timer <= timer_display;
        end
    end

    // Add timeout watchdog
    initial begin
        #10000000; // 10ms timeout
        $display("ERROR: Simulation timeout - possible infinite loop");
        $finish;
    end

    // Test procedure
    initial begin
        // Initialize and setup
        $dumpfile("waves.vcd");
        $dumpvars(0, tb_washing_machine);

        // Initialize all inputs with known states
        clk = 0;
        reset = 0;
        start_stop = 0;
        cycle_select = 0;
        door_open = 0;
        prev_state = 0;
        prev_cycle = 0;
        prev_door_lock = 0;
        prev_buzzer = 0;
        prev_timer = 0;

        // Reset sequence
        #100 reset = 1;
        #100 reset = 0;
        $display("\n=== System Reset Complete at %0t ns ===", $time);

        // Test 1: Normal delicate cycle with longer timeouts
        $display("\n=== Test 1: Normal Delicate Cycle at %0t ns ===", $time);
        cycle_select = 0;  // Ensure DELICATE cycle
        #100 start_stop = 1;
        #100 start_stop = 0;
        wait_for_state(FILL, 1000);    // Increased timeout
        wait_for_state(WASH, 1000);    // Increased timeout
        wait_for_state(DRAIN, 1000);   // Increased timeout
        wait_for_state(RINSE, 1000);   // Increased timeout
        wait_for_state(SPIN, 1000);    // Increased timeout
        wait_for_state(COMPLETE, 1000); // Increased timeout

        // Test 2: Door open during operation
        $display("\n=== Test 2: Door Open During Wash at %0t ns ===", $time);
        #20 start_stop = 1;
        #20 start_stop = 0;
        wait_for_state(FILL, 200);
        #100;  // Wait for WASH state
        door_open = 1;
        wait_for_state(PAUSED, 100);
        #20 door_open = 0;
        #20 start_stop = 1;
        #20 start_stop = 0;
        wait_for_state(WASH, 200);

        // Test 3: Cycle selection
        $display("\n=== Test 3: Cycle Selection at %0t ns ===", $time);
        #20 reset = 1;    // Reset to known state
        #20 reset = 0;
        wait_for_state(IDLE, 100);
        
        #20 cycle_select = 1;
        #20 cycle_select = 0;
        #20;  // Wait for cycle to update
        if (led_cycle !== 2'b01) begin
            $display("ERROR: Failed to switch to NORMAL cycle");
            error_count = error_count + 1;
        end
        
        #20 cycle_select = 1;
        #20 cycle_select = 0;
        #20;  // Wait for cycle to update
        if (led_cycle !== 2'b10) begin
            $display("ERROR: Failed to switch to HEAVY cycle");
            error_count = error_count + 1;
        end

        // Test 4: Reset during operation
        reset = 1;
        #40 reset = 0;
        wait_for_state(IDLE, 500);

        // Display final results
        #200;
        $display("\n=== Test Summary ===");
        $display("Total Errors: %0d", error_count);
        $display("Total Time: %0t ns", $time);
        $finish;
    end

endmodule

waves.vcd
$date
	Thu Mar 20 15:05:12 2025
$end
$version
	Icarus Verilog
$end
$timescale
	1ps
$end
$scope module tb_washing_machine $end
$var wire 4 ! timer_display [3:0] $end
$var wire 3 " led_state [2:0] $end
$var wire 2 # led_cycle [1:0] $end
$var wire 1 $ door_lock $end
$var wire 1 % buzzer $end
$var parameter 3 & COMPLETE $end
$var parameter 3 ' DRAIN $end
$var parameter 4 ( DRAIN_TIME $end
$var parameter 3 ) FILL $end
$var parameter 4 * FILL_TIME $end
$var parameter 3 + IDLE $end
$var parameter 3 , PAUSED $end
$var parameter 3 - RINSE $end
$var parameter 4 . RINSE_TIME $end
$var parameter 3 / SPIN $end
$var parameter 4 0 SPIN_TIME $end
$var parameter 3 1 WASH $end
$var parameter 4 2 WASH_TIME $end
$var reg 1 3 clk $end
$var reg 1 4 cycle_select $end
$var reg 1 5 door_open $end
$var reg 1 6 prev_buzzer $end
$var reg 2 7 prev_cycle [1:0] $end
$var reg 1 8 prev_door_lock $end
$var reg 3 9 prev_state [2:0] $end
$var reg 4 : prev_timer [3:0] $end
$var reg 1 ; reset $end
$var reg 1 < start_stop $end
$var integer 32 = error_count [31:0] $end
$scope module uut $end
$var wire 1 3 clk $end
$var wire 1 4 cycle_select $end
$var wire 1 5 door_open $end
$var wire 1 ; reset $end
$var wire 1 < start_stop $end
$var parameter 3 > COMPLETE $end
$var parameter 2 ? DELICATE $end
$var parameter 3 @ DRAIN $end
$var parameter 3 A FILL $end
$var parameter 2 B HEAVY $end
$var parameter 3 C IDLE $end
$var parameter 2 D NORMAL $end
$var parameter 3 E PAUSED $end
$var parameter 3 F RINSE $end
$var parameter 3 G SPIN $end
$var parameter 3 H WASH $end
$var reg 1 % buzzer $end
$var reg 3 I current_state [2:0] $end
$var reg 1 $ door_lock $end
$var reg 6 J drain_time [5:0] $end
$var reg 6 K fill_time [5:0] $end
$var reg 2 L led_cycle [1:0] $end
$var reg 3 M led_state [2:0] $end
$var reg 3 N next_state [2:0] $end
$var reg 6 O rinse_time [5:0] $end
$var reg 2 P selected_cycle [1:0] $end
$var reg 6 Q spin_time [5:0] $end
$var reg 1 R state_changed $end
$var reg 6 S timer [5:0] $end
$var reg 4 T timer_display [3:0] $end
$var reg 6 U wash_time [5:0] $end
$upscope $end
$scope task check_timer $end
$var reg 4 V expected [3:0] $end
$var reg 512 W state_name [511:0] $end
$upscope $end
$scope task print_state $end
$var reg 3 X state [2:0] $end
$upscope $end
$scope task wait_for_state $end
$var reg 3 Y expected_state [2:0] $end
$var reg 32 Z timeout [31:0] $end
$scope begin wait_state $end
$upscope $end
$upscope $end
$upscope $end
$enddefinitions $end
$comment Show the parameter values. $end
$dumpall
b10 H
b101 G
b100 F
b110 E
b1 D
b0 C
b10 B
b1 A
b11 @
b0 ?
b111 >
b1010 2
b10 1
b1000 0
b101 /
b101 .
b100 -
b110 ,
b0 +
b101 *
b1 )
b11 (
b11 '
b111 &
$end
#0
$dumpvars
bx Z
bx Y
bx X
bx W
bx V
bx U
bx T
bx S
xR
bx Q
bx P
bx O
bx N
bx M
bx L
bx K
bx J
bx I
b0 =
0<
0;
b0 :
b0 9
08
b0 7
06
05
04
03
x%
x$
bx #
bx "
bx !
$end
#10000
b0 !
b0 T
b0 S
13
#20000
03
#30000
13
#40000
03
#50000
13
#60000
03
#70000
13
#80000
03
#90000
13
#100000
b0 #
b0 L
b101 K
b1010 U
b11 J
b101 O
b1000 Q
0%
0$
b0 N
b0 "
b0 M
b0 P
b0 I
03
1;
#110000
0R
13
#120000
03
#130000
13
#140000
03
#150000
13
#160000
03
#170000
13
#180000
03
#190000
13
#200000
03
0;
#210000
13
#220000
03
#230000
13
#240000
03
#250000
13
#260000
03
#270000
13
#280000
03
#290000
13
#300000
b1 N
03
1<
#310000
1$
b1 "
b1 M
b1 I
1R
13
#320000
03
#330000
18
b1 9
0R
b1 X
13
#340000
03
#350000
b1 !
b1 T
b1 S
13
#360000
03
#370000
b10 !
b10 T
b10 S
b1 :
13
#380000
03
#390000
b11 !
b11 T
b11 S
b10 :
13
#400000
03
b1111101000 Z
b1 Y
0<
#410000
b10 N
b100 !
b100 T
b100 S
b11 :
b10 Y
13
#420000
03
#430000
b10 "
b10 M
b10 I
b100 :
1R
13
#440000
03
#450000
b0 !
b0 T
b0 S
b10 9
0R
b11 Y
b10 X
13
#460000
03
#470000
b1 !
b1 T
b1 S
b0 :
13
#480000
03
#490000
b10 !
b10 T
b10 S
b1 :
13
#500000
03
#510000
b11 !
b11 T
b11 S
b10 :
13
#520000
03
#530000
b100 !
b100 T
b100 S
b11 :
13
#540000
03
#550000
b101 !
b101 T
b101 S
b100 :
13
#560000
03
#570000
b110 !
b110 T
b110 S
b101 :
13
#580000
03
#590000
b111 !
b111 T
b111 S
b110 :
13
#600000
03
#610000
b1000 !
b1000 T
b1000 S
b111 :
13
#620000
03
#630000
b11 N
b1001 !
b1001 T
b1001 S
b1000 :
13
#640000
03
#650000
b100 N
b11 "
b11 M
b11 I
b1001 :
1R
13
#660000
03
#670000
b0 !
b0 T
b100 "
b100 M
b0 S
b100 I
b11 9
b100 Y
b11 X
13
#680000
03
#690000
b0 :
b100 9
0R
b101 Y
b100 X
13
#700000
03
#710000
b1 !
b1 T
b1 S
13
#720000
03
#730000
b10 !
b10 T
b10 S
b1 :
13
#740000
03
#750000
b11 !
b11 T
b11 S
b10 :
13
#760000
03
#770000
b101 N
b100 !
b100 T
b100 S
b11 :
13
#780000
03
#790000
b101 "
b101 M
b101 I
b100 :
1R
13
#800000
03
#810000
b0 !
b0 T
b0 S
b101 9
0R
b111 Y
b101 X
13
#820000
03
#830000
b1 !
b1 T
b1 S
b0 :
13
#840000
03
#850000
b10 !
b10 T
b10 S
b1 :
13
#860000
03
#870000
b11 !
b11 T
b11 S
b10 :
13
#880000
03
#890000
b100 !
b100 T
b100 S
b11 :
13
#900000
03
#910000
b101 !
b101 T
b101 S
b100 :
13
#920000
03
#930000
b110 !
b110 T
b110 S
b101 :
13
#940000
03
#950000
b111 N
b111 !
b111 T
b111 S
b110 :
13
#960000
03
#970000
1%
0$
b111 "
b111 M
b111 I
b111 :
1R
13
#980000
03
#990000
b0 !
b0 T
b0 S
16
08
b111 9
0R
b111 X
13
#1000000
03
#1010000
0%
b0 "
b0 M
b0 I
b0 :
1R
b1 N
13
1<
#1020000
03
#1030000
06
b0 9
0R
b0 X
b0 N
13
b11001000 Z
b1 Y
0<
